odoo9_addon_account_banking_pain_base-9.0.1.0.0.99.dev47-py2.7-nspkg.pth
odoo9_addon_account_banking_pain_base-9.0.1.0.0.99.dev47.dist-info/METADATA
odoo9_addon_account_banking_pain_base-9.0.1.0.0.99.dev47.dist-info/RECORD
odoo9_addon_account_banking_pain_base-9.0.1.0.0.99.dev47.dist-info/WHEEL
odoo9_addon_account_banking_pain_base-9.0.1.0.0.99.dev47.dist-info/namespace_packages.txt
odoo9_addon_account_banking_pain_base-9.0.1.0.0.99.dev47.dist-info/top_level.txt
odoo_addons/account_banking_pain_base/README.rst
odoo_addons/account_banking_pain_base/__init__.py
odoo_addons/account_banking_pain_base/__openerp__.py
odoo_addons/account_banking_pain_base/post_install.py
odoo_addons/account_banking_pain_base/i18n/account_banking_pain_base.pot
odoo_addons/account_banking_pain_base/i18n/am.po
odoo_addons/account_banking_pain_base/i18n/ar.po
odoo_addons/account_banking_pain_base/i18n/ca.po
odoo_addons/account_banking_pain_base/i18n/ca_ES.po
odoo_addons/account_banking_pain_base/i18n/da.po
odoo_addons/account_banking_pain_base/i18n/de.po
odoo_addons/account_banking_pain_base/i18n/el_GR.po
odoo_addons/account_banking_pain_base/i18n/es.po
odoo_addons/account_banking_pain_base/i18n/es_ES.po
odoo_addons/account_banking_pain_base/i18n/es_MX.po
odoo_addons/account_banking_pain_base/i18n/es_VE.po
odoo_addons/account_banking_pain_base/i18n/eu.po
odoo_addons/account_banking_pain_base/i18n/fi.po
odoo_addons/account_banking_pain_base/i18n/fr.po
odoo_addons/account_banking_pain_base/i18n/fr_CA.po
odoo_addons/account_banking_pain_base/i18n/fr_CH.po
odoo_addons/account_banking_pain_base/i18n/fr_FR.po
odoo_addons/account_banking_pain_base/i18n/gl.po
odoo_addons/account_banking_pain_base/i18n/hr.po
odoo_addons/account_banking_pain_base/i18n/hr_HR.po
odoo_addons/account_banking_pain_base/i18n/hu.po
odoo_addons/account_banking_pain_base/i18n/it.po
odoo_addons/account_banking_pain_base/i18n/lv.po
odoo_addons/account_banking_pain_base/i18n/nb.po
odoo_addons/account_banking_pain_base/i18n/nb_NO.po
odoo_addons/account_banking_pain_base/i18n/nl.po
odoo_addons/account_banking_pain_base/i18n/nl_BE.po
odoo_addons/account_banking_pain_base/i18n/nl_NL.po
odoo_addons/account_banking_pain_base/i18n/pt.po
odoo_addons/account_banking_pain_base/i18n/pt_BR.po
odoo_addons/account_banking_pain_base/i18n/pt_PT.po
odoo_addons/account_banking_pain_base/i18n/ro.po
