Metadata-Version: 2.1
Name: odoo9-addon-account-banking-pain-base
Version: 9.0.1.0.0.99.dev47
Summary: Base module for PAIN file generation
Home-page: https://github.com/OCA/bank-payment
Author: Akretion, Noviat, Tecnativa, Odoo Community Association (OCA)
Author-email: support@odoo-community.org
License: AGPL-3
Platform: UNKNOWN
Classifier: Programming Language :: Python
Classifier: Framework :: Odoo
Classifier: License :: OSI Approved :: GNU Affero General Public License v3
Requires-Python: ~=2.7
Requires-Dist: lxml
Requires-Dist: odoo9-addon-account-payment-order
Requires-Dist: odoo (<9.1a,>=9.0a)
Requires-Dist: unidecode
